{
  "resourceType": "http://ohs.dev/StructureDefinition/ViewConfig",
  "viewType": "PatientCard",
  "property": [
    {
      "name": "showStatusChip",
      "type": "boolean",
      "valueBoolean": true
    },
    {
      "name": "showAge",
      "type": "boolean",
      "valueBoolean": true
    },
    {
      "name": "showGender",
      "type": "boolean",
      "valueBoolean": true
    },
    {
      "name": "elevation",
      "type": "decimal",
      "valueDecimal": 2.0
    },
    {
      "name": "padding",
      "type": "decimal",
      "valueDecimal": 16.0
    }
  ]
}
